neophile/__init__.py
neophile/cli.py
neophile/config.py
neophile/exceptions.py
neophile/factory.py
neophile/pr.py
neophile/processor.py
neophile/repository.py
neophile/analysis/__init__.py
neophile/analysis/base.py
neophile/analysis/pre_commit.py
neophile/analysis/python.py
neophile/inventory/__init__.py
neophile/inventory/github.py
neophile/inventory/version.py
neophile/models/__init__.py
neophile/models/dependencies.py
neophile/scanner/__init__.py
neophile/scanner/base.py
neophile/scanner/pre_commit.py
neophile/update/__init__.py
neophile/update/base.py
neophile/update/pre_commit.py
neophile/update/python.py
neophile-2.0.1.dist-info/LICENSE
neophile-2.0.1.dist-info/METADATA
neophile-2.0.1.dist-info/WHEEL
neophile-2.0.1.dist-info/entry_points.txt
neophile-2.0.1.dist-info/top_level.txt
neophile-2.0.1.dist-info/RECORD
