Metadata-Version: 2.1
Name: neophile
Version: 2.0.1
Summary: Scan repositories for obsolete versions
License: MIT License
Project-URL: Homepage, https://neophile.lsst.io/
Project-URL: Source, https://github.com/lsst-sqre/neophile
Keywords: rubin,lsst
Classifier: Development Status :: 4 - Beta
Classifier: License :: OSI Approved :: MIT License
Classifier: Programming Language :: Python
Classifier: Programming Language :: Python :: 3
Classifier: Programming Language :: Python :: 3.11
Classifier: Intended Audience :: Developers
Classifier: Natural Language :: English
Classifier: Operating System :: POSIX
Classifier: Typing :: Typed
Requires-Python: >=3.11
License-File: LICENSE
Requires-Dist: GitPython
Requires-Dist: click (!=8.1.4)
Requires-Dist: gidgethub
Requires-Dist: httpx
Requires-Dist: packaging
Requires-Dist: pydantic (<2)
Requires-Dist: ruamel.yaml
Requires-Dist: safir
Requires-Dist: semver
Provides-Extra: dev
Requires-Dist: cryptography ; extra == 'dev'
Requires-Dist: mypy ; extra == 'dev'
Requires-Dist: pytest ; extra == 'dev'
Requires-Dist: pytest-asyncio ; extra == 'dev'
Requires-Dist: pytest-cov ; extra == 'dev'
Requires-Dist: pytest-sugar ; extra == 'dev'
Requires-Dist: respx ; extra == 'dev'
Requires-Dist: autodoc-pydantic ; extra == 'dev'
Requires-Dist: documenteer[guide] ; extra == 'dev'
Requires-Dist: scriv[toml] ; extra == 'dev'
Requires-Dist: sphinx-click ; extra == 'dev'
